Workbook

Sheet Setup
A1: Personal Finance Tracker — Setup
A3: Your Name | B3: Your Name
A4: Currency Symbol | B4: $
A5: Tracking Start Month | B5: =DATE(2026,1,1) -> 46023 | C5: Enter the 1st of the month you want to start logging (e.g. this month).
A7: Yearly Goals
A8: Net Worth Goal | B8: 50000
A9: Savings Balance Goal | B9: 20000
A10: Debt Payoff Goal (balance to reach) | B10: 0
A12: Investment Allocation Targets
A13: Stocks % | B13: 0.6
A14: Bonds % | B14: 0.2
A15: Cash % | B15: 0.1
A16: Other % | B16: 0.1
A17: Total | B17: =SUM(B13:B16) -> 1 | C17: Should total 100% — turns red if not.

Sheet Monthly Log
A1: Month | B1: Income | C1: Housing | D1: Food | E1: Transport | F1: Utilities | G1: Entertainment | H1: Other | I1: Subscriptions | J1: Savings Contribution | K1: Investment Contribution | L1: Savings Balance | M1: Investment Balance | N1: Emergency Fund Balance | O1: Debt Balance | P1: Debt Payment | Q1: Notes | R1: Status
A2: =Setup!$B$5 -> 46023 | R2: =IF(B2="","—","✓ Logged") -> —
A3: =EDATE(A2,1) -> 46054 | R3: =IF(B3="","—","✓ Logged") -> —
A4: =EDATE(A3,1) -> 46082 | R4: =IF(B4="","—","✓ Logged") -> —
A5: =EDATE(A4,1) -> 46113 | R5: =IF(B5="","—","✓ Logged") -> —
A6: =EDATE(A5,1) -> 46143 | R6: =IF(B6="","—","✓ Logged") -> —
A7: =EDATE(A6,1) -> 46174 | R7: =IF(B7="","—","✓ Logged") -> —
A8: =EDATE(A7,1) -> 46204 | R8: =IF(B8="","—","✓ Logged") -> —
A9: =EDATE(A8,1) -> 46235 | R9: =IF(B9="","—","✓ Logged") -> —
A10: =EDATE(A9,1) -> 46266 | R10: =IF(B10="","—","✓ Logged") -> —
A11: =EDATE(A10,1) -> 46296 | R11: =IF(B11="","—","✓ Logged") -> —
A12: =EDATE(A11,1) -> 46327 | R12: =IF(B12="","—","✓ Logged") -> —
A13: =EDATE(A12,1) -> 46357 | R13: =IF(B13="","—","✓ Logged") -> —
A14: =EDATE(A13,1) -> 46388 | R14: =IF(B14="","—","✓ Logged") -> —
... A61: =EDATE(A60,1) -> 47818 | R61: =IF(B61="","—","✓ Logged") -> —
A63: Just type your numbers for the current month — Month and Status fill themselves in.

Sheet Dashboard
A1: Personal Finance Dashboard
A2: Your latest snapshot — recalculates automatically from Monthly Log.
A4: =IF(Engine!$B$64=0,"Welcome! Log your first month on the Monthly Log tab to get started.",IF(TODAY()-Engine!$B$65>35,"⚠ It's been a while — time to log this month on the Monthly Log tab.","✓ You're up to date for this month.")) -> Welcome! Log your first month on the Monthly Log tab to get started.
A6: This Month's Snapshot | E6: Budget vs. the 50/30/20 Rule
A7: KPI | B7: Value | E7: Category | F7: Actual | G7: Target | H7: vs Target
A8: Net Worth | B8: =IF(Engine!$B$64=0,"",INDEX(Engine!$D$2:$D$61,Engine!$B$64)) | E8: Needs | F8: =IF(Engine!$B$64=0,"",INDEX(Engine!$N$2:$N$61,Engine!$B$64)) | G8: 0.5 | H8: =IF(F8="","",F8-G8)
A9: Monthly Cash Flow | B9: =IF(Engine!$B$64=0,"",INDEX(Engine!$C$2:$C$61,Engine!$B$64)) | E9: Wants | F9: =IF(Engine!$B$64=0,"",INDEX(Engine!$O$2:$O$61,Engine!$B$64)) | G9: 0.3 | H9: =IF(F9="","",F9-G9)
A10: Savings Rate | B10: =IF(Engine!$B$64=0,"",INDEX(Engine!$E$2:$E$61,Engine!$B$64)) | E10: Savings | F10: =IF(Engine!$B$64=0,"",INDEX(Engine!$P$2:$P$61,Engine!$B$64)) | G10: 0.2 | H10: =IF(F10="","",F10-G10)
A11: Emergency Fund (months) | B11: =IF(Engine!$B$64=0,"",INDEX(Engine!$F$2:$F$61,Engine!$B$64))
A12: FIRE Progress | B12: =IF(Engine!$B$64=0,"",INDEX(Engine!$J$2:$J$61,Engine!$B$64)) | E12: Investment Allocation Target
A13: Debt-to-Income | B13: =IF(Engine!$B$64=0,"",INDEX(Engine!$G$2:$G$61,Engine!$B$64)) | E13: Asset Class | F13: Target %
A14: Financial Health Score | B14: =IF(Engine!$B$64=0,"",INDEX(Engine!$H$2:$H$61,Engine!$B$64)) | E14: Stocks | F14: =Setup!$B$13 -> 0.6
E15: Bonds | F15: =Setup!$B$14 -> 0.2
A16: Yearly Goals Progress | E16: Cash | F16: =Setup!$B$15 -> 0.1
A17: Goal | B17: Progress | E17: Other | F17: =Setup!$B$16 -> 0.1
A18: Net Worth | B18: =IF(OR(IF(Engine!$B$64=0,"",INDEX(Engine!$D$2:$D$61,Engine!$B$64))="",Setup!$B$8=0),"",MAX(0,MIN(IF(Engine!$B$64=0,"",INDEX(Engine!$D$2:$D$61,Engine!$B$64))/Setup!$B$8,1)))
A19: Savings Balance | B19: =IF(OR(IF(Engine!$B$64=0,"",INDEX('Monthly Log'!$L$2:$L$61,Engine!$B$64))="",Setup!$B$9=0),"",MAX(0,MIN(IF(Engine!$B$64=0,"",INDEX('Monthly Log'!$L$2:$L$61,Engine!$B$64))/Setup!$B$9,1)))
A20: Debt Payoff | B20: =IF(IF(Engine!$B$64=0,"",INDEX('Monthly Log'!$O$2:$O$61,Engine!$B$64))="","",IF(IF(Engine!$B$64=0,"",INDEX('Monthly Log'!$O$2:$O$61,Engine!$B$64))<=Setup!$B$10,1,MAX(0,MIN((Engine!$B$66-IF(Engine!$B$64=0,"",INDEX('Monthly Log'!$O$2:$O$61,Engine!$B$64)))/MAX(Engine!$B$66-Setup!$B$10,1),1))))
A23: This tracker is for personal organization and educational purposes. It is not licensed financial, investment, or tax advice. For real decisions, consult a qualified financial advisor.

Sheet Yearly Review
A1: Yearly Review
A2: Comparing your latest logged month to 12 months earlier.
A4: YearAgoRowOffset | B4: =MAX(Engine!$B$64-11,1) -> 1
A6: Headline Numbers
A7: Metric | B7: 12 Months Ago | C7: Latest | D7: Change
A8: Net Worth | B8: =IF(Engine!$B$64=0,"",INDEX(Engine!$D$2:$D$61,$B$4)) | C8: =IF(Engine!$B$64=0,"",INDEX(Engine!$D$2:$D$61,Engine!$B$64)) | D8: =IF(OR(B8="",C8=""),"",C8-B8)
A9: Savings Rate | B9: =IF(Engine!$B$64=0,"",INDEX(Engine!$E$2:$E$61,$B$4)) | C9: =IF(Engine!$B$64=0,"",INDEX(Engine!$E$2:$E$61,Engine!$B$64)) | D9: =IF(OR(B9="",C9=""),"",C9-B9)
A11: Spending by Category
A12: Category | B12: 12 Months Ago | C12: Latest | D12: Change
A13: Housing | B13: =IF(Engine!$B$64=0,"",INDEX('Monthly Log'!$C$2:$C$61,$B$4)) | C13: =IF(Engine!$B$64=0,"",INDEX('Monthly Log'!$C$2:$C$61,Engine!$B$64)) | D13: =IF(OR(B13="",C13=""),"",C13-B13)
A14: Food | B14: =IF(Engine!$B$64=0,"",INDEX('Monthly Log'!$D$2:$D$61,$B$4)) | C14: =IF(Engine!$B$64=0,"",INDEX('Monthly Log'!$D$2:$D$61,Engine!$B$64)) | D14: =IF(OR(B14="",C14=""),"",C14-B14)
A15: Transport | B15: =IF(Engine!$B$64=0,"",INDEX('Monthly Log'!$E$2:$E$61,$B$4)) | C15: =IF(Engine!$B$64=0,"",INDEX('Monthly Log'!$E$2:$E$61,Engine!$B$64)) | D15: =IF(OR(B15="",C15=""),"",C15-B15)
A16: Utilities | B16: =IF(Engine!$B$64=0,"",INDEX('Monthly Log'!$F$2:$F$61,$B$4)) | C16: =IF(Engine!$B$64=0,"",INDEX('Monthly Log'!$F$2:$F$61,Engine!$B$64)) | D16: =IF(OR(B16="",C16=""),"",C16-B16)
A17: Entertainment | B17: =IF(Engine!$B$64=0,"",INDEX('Monthly Log'!$G$2:$G$61,$B$4)) | C17: =IF(Engine!$B$64=0,"",INDEX('Monthly Log'!$G$2:$G$61,Engine!$B$64)) | D17: =IF(OR(B17="",C17=""),"",C17-B17)
A18: Other | B18: =IF(Engine!$B$64=0,"",INDEX('Monthly Log'!$H$2:$H$61,$B$4)) | C18: =IF(Engine!$B$64=0,"",INDEX('Monthly Log'!$H$2:$H$61,Engine!$B$64)) | D18: =IF(OR(B18="",C18=""),"",C18-B18)
A19: Subscriptions | B19: =IF(Engine!$B$64=0,"",INDEX('Monthly Log'!$I$2:$I$61,$B$4)) | C19: =IF(Engine!$B$64=0,"",INDEX('Monthly Log'!$I$2:$I$61,Engine!$B$64)) | D19: =IF(OR(B19="",C19=""),"",C19-B19)
A22: =IF(B8="","Log at least one month to see your yearly review here.","Over the last 12 months, your net worth has "&IF(D8>=0,"grown","dropped")&" by "&TEXT(ABS(D8),"$#,##0")&" ("&TEXT(IF(B8=0,0,D8/ABS(B8)),"0.0%")&"), and your savings rate has moved from "&TEXT(B9,"0.0%")&" to "&TEXT(C9,"0.0%")&".") -> Log at least one month to see your yearly review here.

Sheet Engine
A1: TotalExpenses | B1: TotalOutgoings | C1: CashFlow | D1: NetWorth | E1: SavingsRate | F1: EFMonths | G1: DTI | H1: HealthScore | I1: FireNumber | J1: FireProgress | K1: NeedsAmt | L1: WantsAmt | M1: SavingsAllocAmt | N1: NeedsPct | O1: WantsPct | P1: SavingsPct | Q1: ChartNetWorth | R1: ChartSavingsRate | S1: ChartCashFlow | T1: ChartFireProgress | U1: ChartHealthScore
A2: =IF('Monthly Log'!B2="","",'Monthly Log'!C2+'Monthly Log'!D2+'Monthly Log'!E2+'Monthly Log'!F2+'Monthly Log'!G2+'Monthly Log'!H2) | B2: =IF('Monthly Log'!B2="","",A2+'Monthly Log'!I2) | C2: =IF('Monthly Log'!B2="","",'Monthly Log'!B2-A2-'Monthly Log'!I2-'Monthly Log'!P2-'Monthly Log'!J2-'Monthly Log'!K2) | D2: =IF('Monthly Log'!B2="","",'Monthly Log'!L2+'Monthly Log'!M2+'Monthly Log'!N2-'Monthly Log'!O2) | E2: =IF('Monthly Log'!B2="","",IF('Monthly Log'!B2=0,0,('Monthly Log'!J2+'Monthly Log'!K2)/'Monthly Log'!B2)) | F2: =IF('Monthly Log'!B2="","",IF(B2=0,0,'Monthly Log'!N2/B2)) | G2: =IF('Monthly Log'!B2="","",IF('Monthly Log'!B2=0,0,'Monthly Log'!P2/'Monthly Log'!B2)) | H2: =IF('Monthly Log'!B2="","",AVERAGE(MIN(E2*100/20*100,100),MIN(F2/6*100,100),MAX(0,100-G2*100*4),IF(C2>=0,100,MAX(0,100+(IF('Monthly Log'!B2=0,0,C2/'Monthly Log'!B2*100)*2))))) | I2: =IF('Monthly Log'!B2="","",B2*12*25) | J2: =IF('Monthly Log'!B2="","",IF(I2=0,0,('Monthly Log'!L2+'Monthly Log'!M2)/I2)) | K2: =IF('Monthly Log'!B2="","",'Monthly Log'!C2+'Monthly Log'!D2+'Monthly Log'!E2+'Monthly Log'!F2+'Monthly Log'!P2) | L2: =IF('Monthly Log'!B2="","",'Monthly Log'!G2+'Monthly Log'!H2+'Monthly Log'!I2) | M2: =IF('Monthly Log'!B2="","",'Monthly Log'!J2+'Monthly Log'!K2) | N2: =IF('Monthly Log'!B2="","",IF('Monthly Log'!B2=0,0,K2/'Monthly Log'!B2)) | O2: =IF('Monthly Log'!B2="","",IF('Monthly Log'!B2=0,0,L2/'Monthly Log'!B2)) | P2: =IF('Monthly Log'!B2="","",IF('Monthly Log'!B2=0,0,M2/'Monthly Log'!B2)) | Q2: =IF(D2="",NA(),D2) -> #N/A | R2: =IF(E2="",NA(),E2) -> #N/A | S2: =IF(C2="",NA(),C2) -> #N/A | T2: =IF(J2="",NA(),J2) -> #N/A | U2: =IF(H2="",NA(),H2) -> #N/A
A3: =IF('Monthly Log'!B3="","",'Monthly Log'!C3+'Monthly Log'!D3+'Monthly Log'!E3+'Monthly Log'!F3+'Monthly Log'!G3+'Monthly Log'!H3) | B3: =IF('Monthly Log'!B3="","",A3+'Monthly Log'!I3) | C3: =IF('Monthly Log'!B3="","",'Monthly Log'!B3-A3-'Monthly Log'!I3-'Monthly Log'!P3-'Monthly Log'!J3-'Monthly Log'!K3) | D3: =IF('Monthly Log'!B3="","",'Monthly Log'!L3+'Monthly Log'!M3+'Monthly Log'!N3-'Monthly Log'!O3) | E3: =IF('Monthly Log'!B3="","",IF('Monthly Log'!B3=0,0,('Monthly Log'!J3+'Monthly Log'!K3)/'Monthly Log'!B3)) | F3: =IF('Monthly Log'!B3="","",IF(B3=0,0,'Monthly Log'!N3/B3)) | G3: =IF('Monthly Log'!B3="","",IF('Monthly Log'!B3=0,0,'Monthly Log'!P3/'Monthly Log'!B3)) | H3: =IF('Monthly Log'!B3="","",AVERAGE(MIN(E3*100/20*100,100),MIN(F3/6*100,100),MAX(0,100-G3*100*4),IF(C3>=0,100,MAX(0,100+(IF('Monthly Log'!B3=0,0,C3/'Monthly Log'!B3*100)*2))))) | I3: =IF('Monthly Log'!B3="","",B3*12*25) | J3: =IF('Monthly Log'!B3="","",IF(I3=0,0,('Monthly Log'!L3+'Monthly Log'!M3)/I3)) | K3: =IF('Monthly Log'!B3="","",'Monthly Log'!C3+'Monthly Log'!D3+'Monthly Log'!E3+'Monthly Log'!F3+'Monthly Log'!P3) | L3: =IF('Monthly Log'!B3="","",'Monthly Log'!G3+'Monthly Log'!H3+'Monthly Log'!I3) | M3: =IF('Monthly Log'!B3="","",'Monthly Log'!J3+'Monthly Log'!K3) | N3: =IF('Monthly Log'!B3="","",IF('Monthly Log'!B3=0,0,K3/'Monthly Log'!B3)) | O3: =IF('Monthly Log'!B3="","",IF('Monthly Log'!B3=0,0,L3/'Monthly Log'!B3)) | P3: =IF('Monthly Log'!B3="","",IF('Monthly Log'!B3=0,0,M3/'Monthly Log'!B3)) | Q3: =IF(D3="",NA(),D3) -> #N/A | R3: =IF(E3="",NA(),E3) -> #N/A | S3: =IF(C3="",NA(),C3) -> #N/A | T3: =IF(J3="",NA(),J3) -> #N/A | U3: =IF(H3="",NA(),H3) -> #N/A
A4: =IF('Monthly Log'!B4="","",'Monthly Log'!C4+'Monthly Log'!D4+'Monthly Log'!E4+'Monthly Log'!F4+'Monthly Log'!G4+'Monthly Log'!H4) | B4: =IF('Monthly Log'!B4="","",A4+'Monthly Log'!I4) | C4: =IF('Monthly Log'!B4="","",'Monthly Log'!B4-A4-'Monthly Log'!I4-'Monthly Log'!P4-'Monthly Log'!J4-'Monthly Log'!K4) | D4: =IF('Monthly Log'!B4="","",'Monthly Log'!L4+'Monthly Log'!M4+'Monthly Log'!N4-'Monthly Log'!O4) | E4: =IF('Monthly Log'!B4="","",IF('Monthly Log'!B4=0,0,('Monthly Log'!J4+'Monthly Log'!K4)/'Monthly Log'!B4)) | F4: =IF('Monthly Log'!B4="","",IF(B4=0,0,'Monthly Log'!N4/B4)) | G4: =IF('Monthly Log'!B4="","",IF('Monthly Log'!B4=0,0,'Monthly Log'!P4/'Monthly Log'!B4)) | H4: =IF('Monthly Log'!B4="","",AVERAGE(MIN(E4*100/20*100,100),MIN(F4/6*100,100),MAX(0,100-G4*100*4),IF(C4>=0,100,MAX(0,100+(IF('Monthly Log'!B4=0,0,C4/'Monthly Log'!B4*100)*2))))) | I4: =IF('Monthly Log'!B4="","",B4*12*25) | J4: =IF('Monthly Log'!B4="","",IF(I4=0,0,('Monthly Log'!L4+'Monthly Log'!M4)/I4)) | K4: =IF('Monthly Log'!B4="","",'Monthly Log'!C4+'Monthly Log'!D4+'Monthly Log'!E4+'Monthly Log'!F4+'Monthly Log'!P4) | L4: =IF('Monthly Log'!B4="","",'Monthly Log'!G4+'Monthly Log'!H4+'Monthly Log'!I4) | M4: =IF('Monthly Log'!B4="","",'Monthly Log'!J4+'Monthly Log'!K4) | N4: =IF('Monthly Log'!B4="","",IF('Monthly Log'!B4=0,0,K4/'Monthly Log'!B4)) | O4: =IF('Monthly Log'!B4="","",IF('Monthly Log'!B4=0,0,L4/'Monthly Log'!B4)) | P4: =IF('Monthly Log'!B4="","",IF('Monthly Log'!B4=0,0,M4/'Monthly Log'!B4)) | Q4: =IF(D4="",NA(),D4) -> #N/A | R4: =IF(E4="",NA(),E4) -> #N/A | S4: =IF(C4="",NA(),C4) -> #N/A | T4: =IF(J4="",NA(),J4) -> #N/A | U4: =IF(H4="",NA(),H4) -> #N/A
A5: =IF('Monthly Log'!B5="","",'Monthly Log'!C5+'Monthly Log'!D5+'Monthly Log'!E5+'Monthly Log'!F5+'Monthly Log'!G5+'Monthly Log'!H5) | B5: =IF('Monthly Log'!B5="","",A5+'Monthly Log'!I5) | C5: =IF('Monthly Log'!B5="","",'Monthly Log'!B5-A5-'Monthly Log'!I5-'Monthly Log'!P5-'Monthly Log'!J5-'Monthly Log'!K5) | D5: =IF('Monthly Log'!B5="","",'Monthly Log'!L5+'Monthly Log'!M5+'Monthly Log'!N5-'Monthly Log'!O5) | E5: =IF('Monthly Log'!B5="","",IF('Monthly Log'!B5=0,0,('Monthly Log'!J5+'Monthly Log'!K5)/'Monthly Log'!B5)) | F5: =IF('Monthly Log'!B5="","",IF(B5=0,0,'Monthly Log'!N5/B5)) | G5: =IF('Monthly Log'!B5="","",IF('Monthly Log'!B5=0,0,'Monthly Log'!P5/'Monthly Log'!B5)) | H5: =IF('Monthly Log'!B5="","",AVERAGE(MIN(E5*100/20*100,100),MIN(F5/6*100,100),MAX(0,100-G5*100*4),IF(C5>=0,100,MAX(0,100+(IF('Monthly Log'!B5=0,0,C5/'Monthly Log'!B5*100)*2))))) | I5: =IF('Monthly Log'!B5="","",B5*12*25) | J5: =IF('Monthly Log'!B5="","",IF(I5=0,0,('Monthly Log'!L5+'Monthly Log'!M5)/I5)) | K5: =IF('Monthly Log'!B5="","",'Monthly Log'!C5+'Monthly Log'!D5+'Monthly Log'!E5+'Monthly Log'!F5+'Monthly Log'!P5) | L5: =IF('Monthly Log'!B5="","",'Monthly Log'!G5+'Monthly Log'!H5+'Monthly Log'!I5) | M5: =IF('Monthly Log'!B5="","",'Monthly Log'!J5+'Monthly Log'!K5) | N5: =IF('Monthly Log'!B5="","",IF('Monthly Log'!B5=0,0,K5/'Monthly Log'!B5)) | O5: =IF('Monthly Log'!B5="","",IF('Monthly Log'!B5=0,0,L5/'Monthly Log'!B5)) | P5: =IF('Monthly Log'!B5="","",IF('Monthly Log'!B5=0,0,M5/'Monthly Log'!B5)) | Q5: =IF(D5="",NA(),D5) -> #N/A | R5: =IF(E5="",NA(),E5) -> #N/A | S5: =IF(C5="",NA(),C5) -> #N/A | T5: =IF(J5="",NA(),J5) -> #N/A | U5: =IF(H5="",NA(),H5) -> #N/A
A6: =IF('Monthly Log'!B6="","",'Monthly Log'!C6+'Monthly Log'!D6+'Monthly Log'!E6+'Monthly Log'!F6+'Monthly Log'!G6+'Monthly Log'!H6) | B6: =IF('Monthly Log'!B6="","",A6+'Monthly Log'!I6) | C6: =IF('Monthly Log'!B6="","",'Monthly Log'!B6-A6-'Monthly Log'!I6-'Monthly Log'!P6-'Monthly Log'!J6-'Monthly Log'!K6) | D6: =IF('Monthly Log'!B6="","",'Monthly Log'!L6+'Monthly Log'!M6+'Monthly Log'!N6-'Monthly Log'!O6) | E6: =IF('Monthly Log'!B6="","",IF('Monthly Log'!B6=0,0,('Monthly Log'!J6+'Monthly Log'!K6)/'Monthly Log'!B6)) | F6: =IF('Monthly Log'!B6="","",IF(B6=0,0,'Monthly Log'!N6/B6)) | G6: =IF('Monthly Log'!B6="","",IF('Monthly Log'!B6=0,0,'Monthly Log'!P6/'Monthly Log'!B6)) | H6: =IF('Monthly Log'!B6="","",AVERAGE(MIN(E6*100/20*100,100),MIN(F6/6*100,100),MAX(0,100-G6*100*4),IF(C6>=0,100,MAX(0,100+(IF('Monthly Log'!B6=0,0,C6/'Monthly Log'!B6*100)*2))))) | I6: =IF('Monthly Log'!B6="","",B6*12*25) | J6: =IF('Monthly Log'!B6="","",IF(I6=0,0,('Monthly Log'!L6+'Monthly Log'!M6)/I6)) | K6: =IF('Monthly Log'!B6="","",'Monthly Log'!C6+'Monthly Log'!D6+'Monthly Log'!E6+'Monthly Log'!F6+'Monthly Log'!P6) | L6: =IF('Monthly Log'!B6="","",'Monthly Log'!G6+'Monthly Log'!H6+'Monthly Log'!I6) | M6: =IF('Monthly Log'!B6="","",'Monthly Log'!J6+'Monthly Log'!K6) | N6: =IF('Monthly Log'!B6="","",IF('Monthly Log'!B6=0,0,K6/'Monthly Log'!B6)) | O6: =IF('Monthly Log'!B6="","",IF('Monthly Log'!B6=0,0,L6/'Monthly Log'!B6)) | P6: =IF('Monthly Log'!B6="","",IF('Monthly Log'!B6=0,0,M6/'Monthly Log'!B6)) | Q6: =IF(D6="",NA(),D6) -> #N/A | R6: =IF(E6="",NA(),E6) -> #N/A | S6: =IF(C6="",NA(),C6) -> #N/A | T6: =IF(J6="",NA(),J6) -> #N/A | U6: =IF(H6="",NA(),H6) -> #N/A
A7: =IF('Monthly Log'!B7="","",'Monthly Log'!C7+'Monthly Log'!D7+'Monthly Log'!E7+'Monthly Log'!F7+'Monthly Log'!G7+'Monthly Log'!H7) | B7: =IF('Monthly Log'!B7="","",A7+'Monthly Log'!I7) | C7: =IF('Monthly Log'!B7="","",'Monthly Log'!B7-A7-'Monthly Log'!I7-'Monthly Log'!P7-'Monthly Log'!J7-'Monthly Log'!K7) | D7: =IF('Monthly Log'!B7="","",'Monthly Log'!L7+'Monthly Log'!M7+'Monthly Log'!N7-'Monthly Log'!O7) | E7: =IF('Monthly Log'!B7="","",IF('Monthly Log'!B7=0,0,('Monthly Log'!J7+'Monthly Log'!K7)/'Monthly Log'!B7)) | F7: =IF('Monthly Log'!B7="","",IF(B7=0,0,'Monthly Log'!N7/B7)) | G7: =IF('Monthly Log'!B7="","",IF('Monthly Log'!B7=0,0,'Monthly Log'!P7/'Monthly Log'!B7)) | H7: =IF('Monthly Log'!B7="","",AVERAGE(MIN(E7*100/20*100,100),MIN(F7/6*100,100),MAX(0,100-G7*100*4),IF(C7>=0,100,MAX(0,100+(IF('Monthly Log'!B7=0,0,C7/'Monthly Log'!B7*100)*2))))) | I7: =IF('Monthly Log'!B7="","",B7*12*25) | J7: =IF('Monthly Log'!B7="","",IF(I7=0,0,('Monthly Log'!L7+'Monthly Log'!M7)/I7)) | K7: =IF('Monthly Log'!B7="","",'Monthly Log'!C7+'Monthly Log'!D7+'Monthly Log'!E7+'Monthly Log'!F7+'Monthly Log'!P7) | L7: =IF('Monthly Log'!B7="","",'Monthly Log'!G7+'Monthly Log'!H7+'Monthly Log'!I7) | M7: =IF('Monthly Log'!B7="","",'Monthly Log'!J7+'Monthly Log'!K7) | N7: =IF('Monthly Log'!B7="","",IF('Monthly Log'!B7=0,0,K7/'Monthly Log'!B7)) | O7: =IF('Monthly Log'!B7="","",IF('Monthly Log'!B7=0,0,L7/'Monthly Log'!B7)) | P7: =IF('Monthly Log'!B7="","",IF('Monthly Log'!B7=0,0,M7/'Monthly Log'!B7)) | Q7: =IF(D7="",NA(),D7) -> #N/A | R7: =IF(E7="",NA(),E7) -> #N/A | S7: =IF(C7="",NA(),C7) -> #N/A | T7: =IF(J7="",NA(),J7) -> #N/A | U7: =IF(H7="",NA(),H7) -> #N/A
A8: =IF('Monthly Log'!B8="","",'Monthly Log'!C8+'Monthly Log'!D8+'Monthly Log'!E8+'Monthly Log'!F8+'Monthly Log'!G8+'Monthly Log'!H8) | B8: =IF('Monthly Log'!B8="","",A8+'Monthly Log'!I8) | C8: =IF('Monthly Log'!B8="","",'Monthly Log'!B8-A8-'Monthly Log'!I8-'Monthly Log'!P8-'Monthly Log'!J8-'Monthly Log'!K8) | D8: =IF('Monthly Log'!B8="","",'Monthly Log'!L8+'Monthly Log'!M8+'Monthly Log'!N8-'Monthly Log'!O8) | E8: =IF('Monthly Log'!B8="","",IF('Monthly Log'!B8=0,0,('Monthly Log'!J8+'Monthly Log'!K8)/'Monthly Log'!B8)) | F8: =IF('Monthly Log'!B8="","",IF(B8=0,0,'Monthly Log'!N8/B8)) | G8: =IF('Monthly Log'!B8="","",IF('Monthly Log'!B8=0,0,'Monthly Log'!P8/'Monthly Log'!B8)) | H8: =IF('Monthly Log'!B8="","",AVERAGE(MIN(E8*100/20*100,100),MIN(F8/6*100,100),MAX(0,100-G8*100*4),IF(C8>=0,100,MAX(0,100+(IF('Monthly Log'!B8=0,0,C8/'Monthly Log'!B8*100)*2))))) | I8: =IF('Monthly Log'!B8="","",B8*12*25) | J8: =IF('Monthly Log'!B8="","",IF(I8=0,0,('Monthly Log'!L8+'Monthly Log'!M8)/I8)) | K8: =IF('Monthly Log'!B8="","",'Monthly Log'!C8+'Monthly Log'!D8+'Monthly Log'!E8+'Monthly Log'!F8+'Monthly Log'!P8) | L8: =IF('Monthly Log'!B8="","",'Monthly Log'!G8+'Monthly Log'!H8+'Monthly Log'!I8) | M8: =IF('Monthly Log'!B8="","",'Monthly Log'!J8+'Monthly Log'!K8) | N8: =IF('Monthly Log'!B8="","",IF('Monthly Log'!B8=0,0,K8/'Monthly Log'!B8)) | O8: =IF('Monthly Log'!B8="","",IF('Monthly Log'!B8=0,0,L8/'Monthly Log'!B8)) | P8: =IF('Monthly Log'!B8="","",IF('Monthly Log'!B8=0,0,M8/'Monthly Log'!B8)) | Q8: =IF(D8="",NA(),D8) -> #N/A | R8: =IF(E8="",NA(),E8) -> #N/A | S8: =IF(C8="",NA(),C8) -> #N/A | T8: =IF(J8="",NA(),J8) -> #N/A | U8: =IF(H8="",NA(),H8) -> #N/A
A9: =IF('Monthly Log'!B9="","",'Monthly Log'!C9+'Monthly Log'!D9+'Monthly Log'!E9+'Monthly Log'!F9+'Monthly Log'!G9+'Monthly Log'!H9) | B9: =IF('Monthly Log'!B9="","",A9+'Monthly Log'!I9) | C9: =IF('Monthly Log'!B9="","",'Monthly Log'!B9-A9-'Monthly Log'!I9-'Monthly Log'!P9-'Monthly Log'!J9-'Monthly Log'!K9) | D9: =IF('Monthly Log'!B9="","",'Monthly Log'!L9+'Monthly Log'!M9+'Monthly Log'!N9-'Monthly Log'!O9) | E9: =IF('Monthly Log'!B9="","",IF('Monthly Log'!B9=0,0,('Monthly Log'!J9+'Monthly Log'!K9)/'Monthly Log'!B9)) | F9: =IF('Monthly Log'!B9="","",IF(B9=0,0,'Monthly Log'!N9/B9)) | G9: =IF('Monthly Log'!B9="","",IF('Monthly Log'!B9=0,0,'Monthly Log'!P9/'Monthly Log'!B9)) | H9: =IF('Monthly Log'!B9="","",AVERAGE(MIN(E9*100/20*100,100),MIN(F9/6*100,100),MAX(0,100-G9*100*4),IF(C9>=0,100,MAX(0,100+(IF('Monthly Log'!B9=0,0,C9/'Monthly Log'!B9*100)*2))))) | I9: =IF('Monthly Log'!B9="","",B9*12*25) | J9: =IF('Monthly Log'!B9="","",IF(I9=0,0,('Monthly Log'!L9+'Monthly Log'!M9)/I9)) | K9: =IF('Monthly Log'!B9="","",'Monthly Log'!C9+'Monthly Log'!D9+'Monthly Log'!E9+'Monthly Log'!F9+'Monthly Log'!P9) | L9: =IF('Monthly Log'!B9="","",'Monthly Log'!G9+'Monthly Log'!H9+'Monthly Log'!I9) | M9: =IF('Monthly Log'!B9="","",'Monthly Log'!J9+'Monthly Log'!K9) | N9: =IF('Monthly Log'!B9="","",IF('Monthly Log'!B9=0,0,K9/'Monthly Log'!B9)) | O9: =IF('Monthly Log'!B9="","",IF('Monthly Log'!B9=0,0,L9/'Monthly Log'!B9)) | P9: =IF('Monthly Log'!B9="","",IF('Monthly Log'!B9=0,0,M9/'Monthly Log'!B9)) | Q9: =IF(D9="",NA(),D9) -> #N/A | R9: =IF(E9="",NA(),E9) -> #N/A | S9: =IF(C9="",NA(),C9) -> #N/A | T9: =IF(J9="",NA(),J9) -> #N/A | U9: =IF(H9="",NA(),H9) -> #N/A
A10: =IF('Monthly Log'!B10="","",'Monthly Log'!C10+'Monthly Log'!D10+'Monthly Log'!E10+'Monthly Log'!F10+'Monthly Log'!G10+'Monthly Log'!H10) | B10: =IF('Monthly Log'!B10="","",A10+'Monthly Log'!I10) | C10: =IF('Monthly Log'!B10="","",'Monthly Log'!B10-A10-'Monthly Log'!I10-'Monthly Log'!P10-'Monthly Log'!J10-'Monthly Log'!K10) | D10: =IF('Monthly Log'!B10="","",'Monthly Log'!L10+'Monthly Log'!M10+'Monthly Log'!N10-'Monthly Log'!O10) | E10: =IF('Monthly Log'!B10="","",IF('Monthly Log'!B10=0,0,('Monthly Log'!J10+'Monthly Log'!K10)/'Monthly Log'!B10)) | F10: =IF('Monthly Log'!B10="","",IF(B10=0,0,'Monthly Log'!N10/B10)) | G10: =IF('Monthly Log'!B10="","",IF('Monthly Log'!B10=0,0,'Monthly Log'!P10/'Monthly Log'!B10)) | H10: =IF('Monthly Log'!B10="","",AVERAGE(MIN(E10*100/20*100,100),MIN(F10/6*100,100),MAX(0,100-G10*100*4),IF(C10>=0,100,MAX(0,100+(IF('Monthly Log'!B10=0,0,C10/'Monthly Log'!B10*100)*2))))) | I10: =IF('Monthly Log'!B10="","",B10*12*25) | J10: =IF('Monthly Log'!B10="","",IF(I10=0,0,('Monthly Log'!L10+'Monthly Log'!M10)/I10)) | K10: =IF('Monthly Log'!B10="","",'Monthly Log'!C10+'Monthly Log'!D10+'Monthly Log'!E10+'Monthly Log'!F10+'Monthly Log'!P10) | L10: =IF('Monthly Log'!B10="","",'Monthly Log'!G10+'Monthly Log'!H10+'Monthly Log'!I10) | M10: =IF('Monthly Log'!B10="","",'Monthly Log'!J10+'Monthly Log'!K10) | N10: =IF('Monthly Log'!B10="","",IF('Monthly Log'!B10=0,0,K10/'Monthly Log'!B10)) | O10: =IF('Monthly Log'!B10="","",IF('Monthly Log'!B10=0,0,L10/'Monthly Log'!B10)) | P10: =IF('Monthly Log'!B10="","",IF('Monthly Log'!B10=0,0,M10/'Monthly Log'!B10)) | Q10: =IF(D10="",NA(),D10) -> #N/A | R10: =IF(E10="",NA(),E10) -> #N/A | S10: =IF(C10="",NA(),C10) -> #N/A | T10: =IF(J10="",NA(),J10) -> #N/A | U10: =IF(H10="",NA(),H10) -> #N/A
A11: =IF('Monthly Log'!B11="","",'Monthly Log'!C11+'Monthly Log'!D11+'Monthly Log'!E11+'Monthly Log'!F11+'Monthly Log'!G11+'Monthly Log'!H11) | B11: =IF('Monthly Log'!B11="","",A11+'Monthly Log'!I11) | C11: =IF('Monthly Log'!B11="","",'Monthly Log'!B11-A11-'Monthly Log'!I11-'Monthly Log'!P11-'Monthly Log'!J11-'Monthly Log'!K11) | D11: =IF('Monthly Log'!B11="","",'Monthly Log'!L11+'Monthly Log'!M11+'Monthly Log'!N11-'Monthly Log'!O11) | E11: =IF('Monthly Log'!B11="","",IF('Monthly Log'!B11=0,0,('Monthly Log'!J11+'Monthly Log'!K11)/'Monthly Log'!B11)) | F11: =IF('Monthly Log'!B11="","",IF(B11=0,0,'Monthly Log'!N11/B11)) | G11: =IF('Monthly Log'!B11="","",IF('Monthly Log'!B11=0,0,'Monthly Log'!P11/'Monthly Log'!B11)) | H11: =IF('Monthly Log'!B11="","",AVERAGE(MIN(E11*100/20*100,100),MIN(F11/6*100,100),MAX(0,100-G11*100*4),IF(C11>=0,100,MAX(0,100+(IF('Monthly Log'!B11=0,0,C11/'Monthly Log'!B11*100)*2))))) | I11: =IF('Monthly Log'!B11="","",B11*12*25) | J11: =IF('Monthly Log'!B11="","",IF(I11=0,0,('Monthly Log'!L11+'Monthly Log'!M11)/I11)) | K11: =IF('Monthly Log'!B11="","",'Monthly Log'!C11+'Monthly Log'!D11+'Monthly Log'!E11+'Monthly Log'!F11+'Monthly Log'!P11) | L11: =IF('Monthly Log'!B11="","",'Monthly Log'!G11+'Monthly Log'!H11+'Monthly Log'!I11) | M11: =IF('Monthly Log'!B11="","",'Monthly Log'!J11+'Monthly Log'!K11) | N11: =IF('Monthly Log'!B11="","",IF('Monthly Log'!B11=0,0,K11/'Monthly Log'!B11)) | O11: =IF('Monthly Log'!B11="","",IF('Monthly Log'!B11=0,0,L11/'Monthly Log'!B11)) | P11: =IF('Monthly Log'!B11="","",IF('Monthly Log'!B11=0,0,M11/'Monthly Log'!B11)) | Q11: =IF(D11="",NA(),D11) -> #N/A | R11: =IF(E11="",NA(),E11) -> #N/A | S11: =IF(C11="",NA(),C11) -> #N/A | T11: =IF(J11="",NA(),J11) -> #N/A | U11: =IF(H11="",NA(),H11) -> #N/A
A12: =IF('Monthly Log'!B12="","",'Monthly Log'!C12+'Monthly Log'!D12+'Monthly Log'!E12+'Monthly Log'!F12+'Monthly Log'!G12+'Monthly Log'!H12) | B12: =IF('Monthly Log'!B12="","",A12+'Monthly Log'!I12) | C12: =IF('Monthly Log'!B12="","",'Monthly Log'!B12-A12-'Monthly Log'!I12-'Monthly Log'!P12-'Monthly Log'!J12-'Monthly Log'!K12) | D12: =IF('Monthly Log'!B12="","",'Monthly Log'!L12+'Monthly Log'!M12+'Monthly Log'!N12-'Monthly Log'!O12) | E12: =IF('Monthly Log'!B12="","",IF('Monthly Log'!B12=0,0,('Monthly Log'!J12+'Monthly Log'!K12)/'Monthly Log'!B12)) | F12: =IF('Monthly Log'!B12="","",IF(B12=0,0,'Monthly Log'!N12/B12)) | G12: =IF('Monthly Log'!B12="","",IF('Monthly Log'!B12=0,0,'Monthly Log'!P12/'Monthly Log'!B12)) | H12: =IF('Monthly Log'!B12="","",AVERAGE(MIN(E12*100/20*100,100),MIN(F12/6*100,100),MAX(0,100-G12*100*4),IF(C12>=0,100,MAX(0,100+(IF('Monthly Log'!B12=0,0,C12/'Monthly Log'!B12*100)*2))))) | I12: =IF('Monthly Log'!B12="","",B12*12*25) | J12: =IF('Monthly Log'!B12="","",IF(I12=0,0,('Monthly Log'!L12+'Monthly Log'!M12)/I12)) | K12: =IF('Monthly Log'!B12="","",'Monthly Log'!C12+'Monthly Log'!D12+'Monthly Log'!E12+'Monthly Log'!F12+'Monthly Log'!P12) | L12: =IF('Monthly Log'!B12="","",'Monthly Log'!G12+'Monthly Log'!H12+'Monthly Log'!I12) | M12: =IF('Monthly Log'!B12="","",'Monthly Log'!J12+'Monthly Log'!K12) | N12: =IF('Monthly Log'!B12="","",IF('Monthly Log'!B12=0,0,K12/'Monthly Log'!B12)) | O12: =IF('Monthly Log'!B12="","",IF('Monthly Log'!B12=0,0,L12/'Monthly Log'!B12)) | P12: =IF('Monthly Log'!B12="","",IF('Monthly Log'!B12=0,0,M12/'Monthly Log'!B12)) | Q12: =IF(D12="",NA(),D12) -> #N/A | R12: =IF(E12="",NA(),E12) -> #N/A | S12: =IF(C12="",NA(),C12) -> #N/A | T12: =IF(J12="",NA(),J12) -> #N/A | U12: =IF(H12="",NA(),H12) -> #N/A
A13: =IF('Monthly Log'!B13="","",'Monthly Log'!C13+'Monthly Log'!D13+'Monthly Log'!E13+'Monthly Log'!F13+'Monthly Log'!G13+'Monthly Log'!H13) | B13: =IF('Monthly Log'!B13="","",A13+'Monthly Log'!I13) | C13: =IF('Monthly Log'!B13="","",'Monthly Log'!B13-A13-'Monthly Log'!I13-'Monthly Log'!P13-'Monthly Log'!J13-'Monthly Log'!K13) | D13: =IF('Monthly Log'!B13="","",'Monthly Log'!L13+'Monthly Log'!M13+'Monthly Log'!N13-'Monthly Log'!O13) | E13: =IF('Monthly Log'!B13="","",IF('Monthly Log'!B13=0,0,('Monthly Log'!J13+'Monthly Log'!K13)/'Monthly Log'!B13)) | F13: =IF('Monthly Log'!B13="","",IF(B13=0,0,'Monthly Log'!N13/B13)) | G13: =IF('Monthly Log'!B13="","",IF('Monthly Log'!B13=0,0,'Monthly Log'!P13/'Monthly Log'!B13)) | H13: =IF('Monthly Log'!B13="","",AVERAGE(MIN(E13*100/20*100,100),MIN(F13/6*100,100),MAX(0,100-G13*100*4),IF(C13>=0,100,MAX(0,100+(IF('Monthly Log'!B13=0,0,C13/'Monthly Log'!B13*100)*2))))) | I13: =IF('Monthly Log'!B13="","",B13*12*25) | J13: =IF('Monthly Log'!B13="","",IF(I13=0,0,('Monthly Log'!L13+'Monthly Log'!M13)/I13)) | K13: =IF('Monthly Log'!B13="","",'Monthly Log'!C13+'Monthly Log'!D13+'Monthly Log'!E13+'Monthly Log'!F13+'Monthly Log'!P13) | L13: =IF('Monthly Log'!B13="","",'Monthly Log'!G13+'Monthly Log'!H13+'Monthly Log'!I13) | M13: =IF('Monthly Log'!B13="","",'Monthly Log'!J13+'Monthly Log'!K13) | N13: =IF('Monthly Log'!B13="","",IF('Monthly Log'!B13=0,0,K13/'Monthly Log'!B13)) | O13: =IF('Monthly Log'!B13="","",IF('Monthly Log'!B13=0,0,L13/'Monthly Log'!B13)) | P13: =IF('Monthly Log'!B13="","",IF('Monthly Log'!B13=0,0,M13/'Monthly Log'!B13)) | Q13: =IF(D13="",NA(),D13) -> #N/A | R13: =IF(E13="",NA(),E13) -> #N/A | S13: =IF(C13="",NA(),C13) -> #N/A | T13: =IF(J13="",NA(),J13) -> #N/A | U13: =IF(H13="",NA(),H13) -> #N/A
... A61: =IF('Monthly Log'!B61="","",'Monthly Log'!C61+'Monthly Log'!D61+'Monthly Log'!E61+'Monthly Log'!F61+'Monthly Log'!G61+'Monthly Log'!H61) | B61: =IF('Monthly Log'!B61="","",A61+'Monthly Log'!I61) | C61: =IF('Monthly Log'!B61="","",'Monthly Log'!B61-A61-'Monthly Log'!I61-'Monthly Log'!P61-'Monthly Log'!J61-'Monthly Log'!K61) | D61: =IF('Monthly Log'!B61="","",'Monthly Log'!L61+'Monthly Log'!M61+'Monthly Log'!N61-'Monthly Log'!O61) | E61: =IF('Monthly Log'!B61="","",IF('Monthly Log'!B61=0,0,('Monthly Log'!J61+'Monthly Log'!K61)/'Monthly Log'!B61)) | F61: =IF('Monthly Log'!B61="","",IF(B61=0,0,'Monthly Log'!N61/B61)) | G61: =IF('Monthly Log'!B61="","",IF('Monthly Log'!B61=0,0,'Monthly Log'!P61/'Monthly Log'!B61)) | H61: =IF('Monthly Log'!B61="","",AVERAGE(MIN(E61*100/20*100,100),MIN(F61/6*100,100),MAX(0,100-G61*100*4),IF(C61>=0,100,MAX(0,100+(IF('Monthly Log'!B61=0,0,C61/'Monthly Log'!B61*100)*2))))) | I61: =IF('Monthly Log'!B61="","",B61*12*25) | J61: =IF('Monthly Log'!B61="","",IF(I61=0,0,('Monthly Log'!L61+'Monthly Log'!M61)/I61)) | K61: =IF('Monthly Log'!B61="","",'Monthly Log'!C61+'Monthly Log'!D61+'Monthly Log'!E61+'Monthly Log'!F61+'Monthly Log'!P61) | L61: =IF('Monthly Log'!B61="","",'Monthly Log'!G61+'Monthly Log'!H61+'Monthly Log'!I61) | M61: =IF('Monthly Log'!B61="","",'Monthly Log'!J61+'Monthly Log'!K61) | N61: =IF('Monthly Log'!B61="","",IF('Monthly Log'!B61=0,0,K61/'Monthly Log'!B61)) | O61: =IF('Monthly Log'!B61="","",IF('Monthly Log'!B61=0,0,L61/'Monthly Log'!B61)) | P61: =IF('Monthly Log'!B61="","",IF('Monthly Log'!B61=0,0,M61/'Monthly Log'!B61)) | Q61: =IF(D61="",NA(),D61) -> #N/A | R61: =IF(E61="",NA(),E61) -> #N/A | S61: =IF(C61="",NA(),C61) -> #N/A | T61: =IF(J61="",NA(),J61) -> #N/A | U61: =IF(H61="",NA(),H61) -> #N/A
A64: LatestRowOffset | B64: =COUNTA('Monthly Log'!B2:B61) -> 0
A65: LatestMonthDate | B65: =IF(B64=0,"",INDEX('Monthly Log'!A2:A61,B64))
A66: FirstLoggedDebt | B66: =IF(B64=0,0,'Monthly Log'!O2) -> 0
