Workbook

Sheet Cover
B2: SIMRAN'S SPACE · TEMPLATES
B4: Personal Finance Dashboard
B7: A modern BI-style view of your money — income, spending, savings goals, investments, subscriptions, net worth, and a single Financial Health Score, all in one file.
B10: WHAT'S INSIDE
B11: ◆ | C11: One Transactions log with keyword auto-categorization — log once, everything else updates
B12: ◆ | C12: Income Tracker and Expense Tracker — source and category breakdowns, not just totals
B13: ◆ | C13: Savings Goals with progress bars and a monthly contribution calculator
B14: ◆ | C14: Investment Tracker with gain/loss and allocation
B15: ◆ | C15: Subscription Tracker that surfaces your real annual subscription cost
B16: ◆ | C16: Net Worth Dashboard, Monthly Trends, and Spending Breakdown, all chart-driven
B17: ◆ | C17: A Financial Health Score — one number, three real inputs, no guesswork
B18: ◆ | C18: An Annual Summary Dashboard that pulls every number below into one page
B21: Built by Simran Tiwari — simrant.github.io

Sheet Read Me
B2: How to use this dashboard
B4: 1. Log every transaction once
B5: The Transactions tab is the only place you enter income or expenses. Everything else — Income Tracker, Expense Tracker, Monthly Trends, Net Worth, the Health Score — is a formula pulling from that one log.
B7: 2. Fill in Savings Goals, Investments, and Subscriptions
B8: These three are separate from Transactions because they're balances and recurring costs, not one-off entries. Update them monthly, not per-transaction.
B10: 3. Check the Financial Health Score
B11: One score, three real inputs: your savings rate, how many months of expenses your cash would cover, and how much of your income subscriptions are quietly eating. No made-up weighting — you can see exactly how it's calculated.
B13: 4. Open the Annual Summary Dashboard last
B14: It's the one page built to actually look at regularly — everything else feeds it.
B16: Why this one's different
B17: Most free budget templates ask you to enter the same numbers twice — once in a transaction log, again in a summary table. This one doesn't: log a transaction once, and it flows into your Income or Expense Tracker, your Monthly Trends, your Net Worth, and your Health Score automatically. It's built to feel like a BI dashboard because that's genuinely what it is — just pointed at your own bank account instead of a company's.

Sheet Keywords
B1: Keyword (lowercase, partial match) | C1: Category
A2: payroll | B2: Income
A3: salary | B3: Income
A4: paycheck | B4: Income
A5: freelance | B5: Income
A6: interest | B6: Income
A7: dividend | B7: Income
A8: starbucks | B8: Dining
A9: coffee | B9: Dining
A10: restaurant | B10: Dining
A11: doordash | B11: Dining
A12: grocery | B12: Groceries
A13: trader joe | B13: Groceries
... A34: 401k | B34: Investing

Sheet Transactions
A1: Date | B1: Description | C1: Type | D1: Category | E1: Suggested Category | F1: Amount
A2: 46025 | B2: Payroll deposit | C2: Income | D2: Income | E2: =IFERROR(INDEX(Keywords!$B$2:$B$34,SUMPRODUCT(MAX((ISNUMBER(SEARCH(Keywords!$A$2:$A$34,B2)))*ROW(Keywords!$A$2:$A$34)))-1),"Uncategorized") -> Income | F2: 4800
A3: 46026 | B3: Whole Foods grocery run | C3: Expense | D3: Groceries | E3: =IFERROR(INDEX(Keywords!$B$2:$B$34,SUMPRODUCT(MAX((ISNUMBER(SEARCH(Keywords!$A$2:$A$34,B3)))*ROW(Keywords!$A$2:$A$34)))-1),"Uncategorized") -> Groceries | F3: -92.4
A4: 46027 | B4: Starbucks coffee | C4: Expense | D4: Dining | E4: =IFERROR(INDEX(Keywords!$B$2:$B$34,SUMPRODUCT(MAX((ISNUMBER(SEARCH(Keywords!$A$2:$A$34,B4)))*ROW(Keywords!$A$2:$A$34)))-1),"Uncategorized") -> Dining | F4: -7.25
A5: 46028 | B5: Rent payment | C5: Expense | D5: Housing | E5: =IFERROR(INDEX(Keywords!$B$2:$B$34,SUMPRODUCT(MAX((ISNUMBER(SEARCH(Keywords!$A$2:$A$34,B5)))*ROW(Keywords!$A$2:$A$34)))-1),"Uncategorized") -> Housing | F5: -1800
A6: 46030 | B6: Uber to airport | C6: Expense | D6: Transport | E6: =IFERROR(INDEX(Keywords!$B$2:$B$34,SUMPRODUCT(MAX((ISNUMBER(SEARCH(Keywords!$A$2:$A$34,B6)))*ROW(Keywords!$A$2:$A$34)))-1),"Uncategorized") -> Transport | F6: -38.2
A7: 46032 | B7: Netflix subscription | C7: Expense | D7: Subscriptions | E7: =IFERROR(INDEX(Keywords!$B$2:$B$34,SUMPRODUCT(MAX((ISNUMBER(SEARCH(Keywords!$A$2:$A$34,B7)))*ROW(Keywords!$A$2:$A$34)))-1),"Uncategorized") -> Subscriptions | F7: -15.49
A8: 46032 | B8: Spotify subscription | C8: Expense | D8: Subscriptions | E8: =IFERROR(INDEX(Keywords!$B$2:$B$34,SUMPRODUCT(MAX((ISNUMBER(SEARCH(Keywords!$A$2:$A$34,B8)))*ROW(Keywords!$A$2:$A$34)))-1),"Uncategorized") -> Subscriptions | F8: -11.99
A9: 46034 | B9: Gym membership | C9: Expense | D9: Health & Fitness | E9: =IFERROR(INDEX(Keywords!$B$2:$B$34,SUMPRODUCT(MAX((ISNUMBER(SEARCH(Keywords!$A$2:$A$34,B9)))*ROW(Keywords!$A$2:$A$34)))-1),"Uncategorized") -> Health & Fitness | F9: -55
A10: 46037 | B10: Freelance project payment | C10: Income | D10: Income | E10: =IFERROR(INDEX(Keywords!$B$2:$B$34,SUMPRODUCT(MAX((ISNUMBER(SEARCH(Keywords!$A$2:$A$34,B10)))*ROW(Keywords!$A$2:$A$34)))-1),"Uncategorized") -> Income | F10: 950
A11: 46040 | B11: Amazon order | C11: Expense | D11: Shopping | E11: =IFERROR(INDEX(Keywords!$B$2:$B$34,SUMPRODUCT(MAX((ISNUMBER(SEARCH(Keywords!$A$2:$A$34,B11)))*ROW(Keywords!$A$2:$A$34)))-1),"Uncategorized") -> Shopping | F11: -68.1
A12: 46042 | B12: Electric bill | C12: Expense | D12: Utilities | E12: =IFERROR(INDEX(Keywords!$B$2:$B$34,SUMPRODUCT(MAX((ISNUMBER(SEARCH(Keywords!$A$2:$A$34,B12)))*ROW(Keywords!$A$2:$A$34)))-1),"Uncategorized") -> Utilities | F12: -81.3
A13: 46044 | B13: Transfer to savings | C13: Expense | D13: Savings | E13: =IFERROR(INDEX(Keywords!$B$2:$B$34,SUMPRODUCT(MAX((ISNUMBER(SEARCH(Keywords!$A$2:$A$34,B13)))*ROW(Keywords!$A$2:$A$34)))-1),"Uncategorized") -> Savings | F13: -600
... A25: 46080 | B25: Interest earned | C25: Income | D25: Income | E25: =IFERROR(INDEX(Keywords!$B$2:$B$34,SUMPRODUCT(MAX((ISNUMBER(SEARCH(Keywords!$A$2:$A$34,B25)))*ROW(Keywords!$A$2:$A$34)))-1),"Uncategorized") -> Income | F25: 15.8
E26: =IF(B26="","",IFERROR(INDEX(Keywords!$B$2:$B$34,SUMPRODUCT(MAX((ISNUMBER(SEARCH(Keywords!$A$2:$A$34,B26)))*ROW(Keywords!$A$2:$A$34)))-1),"Uncategorized"))
E27: =IF(B27="","",IFERROR(INDEX(Keywords!$B$2:$B$34,SUMPRODUCT(MAX((ISNUMBER(SEARCH(Keywords!$A$2:$A$34,B27)))*ROW(Keywords!$A$2:$A$34)))-1),"Uncategorized"))
E28: =IF(B28="","",IFERROR(INDEX(Keywords!$B$2:$B$34,SUMPRODUCT(MAX((ISNUMBER(SEARCH(Keywords!$A$2:$A$34,B28)))*ROW(Keywords!$A$2:$A$34)))-1),"Uncategorized"))
E29: =IF(B29="","",IFERROR(INDEX(Keywords!$B$2:$B$34,SUMPRODUCT(MAX((ISNUMBER(SEARCH(Keywords!$A$2:$A$34,B29)))*ROW(Keywords!$A$2:$A$34)))-1),"Uncategorized"))
E30: =IF(B30="","",IFERROR(INDEX(Keywords!$B$2:$B$34,SUMPRODUCT(MAX((ISNUMBER(SEARCH(Keywords!$A$2:$A$34,B30)))*ROW(Keywords!$A$2:$A$34)))-1),"Uncategorized"))
E31: =IF(B31="","",IFERROR(INDEX(Keywords!$B$2:$B$34,SUMPRODUCT(MAX((ISNUMBER(SEARCH(Keywords!$A$2:$A$34,B31)))*ROW(Keywords!$A$2:$A$34)))-1),"Uncategorized"))
E32: =IF(B32="","",IFERROR(INDEX(Keywords!$B$2:$B$34,SUMPRODUCT(MAX((ISNUMBER(SEARCH(Keywords!$A$2:$A$34,B32)))*ROW(Keywords!$A$2:$A$34)))-1),"Uncategorized"))
E33: =IF(B33="","",IFERROR(INDEX(Keywords!$B$2:$B$34,SUMPRODUCT(MAX((ISNUMBER(SEARCH(Keywords!$A$2:$A$34,B33)))*ROW(Keywords!$A$2:$A$34)))-1),"Uncategorized"))
E34: =IF(B34="","",IFERROR(INDEX(Keywords!$B$2:$B$34,SUMPRODUCT(MAX((ISNUMBER(SEARCH(Keywords!$A$2:$A$34,B34)))*ROW(Keywords!$A$2:$A$34)))-1),"Uncategorized"))
E35: =IF(B35="","",IFERROR(INDEX(Keywords!$B$2:$B$34,SUMPRODUCT(MAX((ISNUMBER(SEARCH(Keywords!$A$2:$A$34,B35)))*ROW(Keywords!$A$2:$A$34)))-1),"Uncategorized"))
E36: =IF(B36="","",IFERROR(INDEX(Keywords!$B$2:$B$34,SUMPRODUCT(MAX((ISNUMBER(SEARCH(Keywords!$A$2:$A$34,B36)))*ROW(Keywords!$A$2:$A$34)))-1),"Uncategorized"))
E37: =IF(B37="","",IFERROR(INDEX(Keywords!$B$2:$B$34,SUMPRODUCT(MAX((ISNUMBER(SEARCH(Keywords!$A$2:$A$34,B37)))*ROW(Keywords!$A$2:$A$34)))-1),"Uncategorized"))
... E65: =IF(B65="","",IFERROR(INDEX(Keywords!$B$2:$B$34,SUMPRODUCT(MAX((ISNUMBER(SEARCH(Keywords!$A$2:$A$34,B65)))*ROW(Keywords!$A$2:$A$34)))-1),"Uncategorized"))

Sheet Income Tracker
B2: Income Tracker
B3: Every number here pulls from the Transactions tab automatically.
B5: Monthly income | F5: Income by source (YTD)
B7: Month | C7: Total Income | F7: Source | G7: Total
B8: Jan 2026 | C8: =SUMIFS(Transactions!$F$2:$F$65,Transactions!$C$2:$C$65,"Income",Transactions!$A$2:$A$65,">="&DATE(2026,1,1),Transactions!$A$2:$A$65,"<="&DATE(2026,1,31)) -> 5764.2 | F8: Salary | G8: =SUMPRODUCT((Transactions!$C$2:$C$65="Income")*ISNUMBER(SEARCH("payroll",Transactions!$B$2:$B$65))*Transactions!$F$2:$F$65) -> 9600
B9: Feb 2026 | C9: =SUMIFS(Transactions!$F$2:$F$65,Transactions!$C$2:$C$65,"Income",Transactions!$A$2:$A$65,">="&DATE(2026,2,1),Transactions!$A$2:$A$65,"<="&DATE(2026,2,28)) -> 4815.8 | F9: Freelance | G9: =SUMPRODUCT((Transactions!$C$2:$C$65="Income")*ISNUMBER(SEARCH("freelance",Transactions!$B$2:$B$65))*Transactions!$F$2:$F$65) -> 950
F10: Interest | G10: =SUMPRODUCT((Transactions!$C$2:$C$65="Income")*ISNUMBER(SEARCH("interest",Transactions!$B$2:$B$65))*Transactions!$F$2:$F$65) -> 30
F11: Dividends | G11: =SUMPRODUCT((Transactions!$C$2:$C$65="Income")*ISNUMBER(SEARCH("dividend",Transactions!$B$2:$B$65))*Transactions!$F$2:$F$65) -> 0

Sheet Expense Tracker
B2: Expense Tracker
B3: Same rule — this all pulls from Transactions, nothing typed in twice.
B5: Monthly expenses | F5: Spending by category (YTD)
B7: Month | C7: Total Expenses | F7: Category | G7: Total
B8: Jan 2026 | C8: =-SUMIFS(Transactions!$F$2:$F$65,Transactions!$C$2:$C$65,"Expense",Transactions!$A$2:$A$65,">="&DATE(2026,1,1),Transactions!$A$2:$A$65,"<="&DATE(2026,1,31)) -> 3269.73 | F8: Dining | G8: =-SUMIFS(Transactions!$F$2:$F$65,Transactions!$D$2:$D$65,F8,Transactions!$C$2:$C$65,"Expense") -> 7.25
B9: Feb 2026 | C9: =-SUMIFS(Transactions!$F$2:$F$65,Transactions!$C$2:$C$65,"Expense",Transactions!$A$2:$A$65,">="&DATE(2026,2,1),Transactions!$A$2:$A$65,"<="&DATE(2026,2,28)) -> 3072.18 | F9: Groceries | G9: =-SUMIFS(Transactions!$F$2:$F$65,Transactions!$D$2:$D$65,F9,Transactions!$C$2:$C$65,"Expense") -> 170.6
F10: Health & Fitness | G10: =-SUMIFS(Transactions!$F$2:$F$65,Transactions!$D$2:$D$65,F10,Transactions!$C$2:$C$65,"Expense") -> 100
F11: Housing | G11: =-SUMIFS(Transactions!$F$2:$F$65,Transactions!$D$2:$D$65,F11,Transactions!$C$2:$C$65,"Expense") -> 3600
F12: Shopping | G12: =-SUMIFS(Transactions!$F$2:$F$65,Transactions!$D$2:$D$65,F12,Transactions!$C$2:$C$65,"Expense") -> 68.1
F13: Subscriptions | G13: =-SUMIFS(Transactions!$F$2:$F$65,Transactions!$D$2:$D$65,F13,Transactions!$C$2:$C$65,"Expense") -> 54.96
F14: Transport | G14: =-SUMIFS(Transactions!$F$2:$F$65,Transactions!$D$2:$D$65,F14,Transactions!$C$2:$C$65,"Expense") -> 59.7
F15: Travel | G15: =-SUMIFS(Transactions!$F$2:$F$65,Transactions!$D$2:$D$65,F15,Transactions!$C$2:$C$65,"Expense") -> 0
F16: Utilities | G16: =-SUMIFS(Transactions!$F$2:$F$65,Transactions!$D$2:$D$65,F16,Transactions!$C$2:$C$65,"Expense") -> 81.3

Sheet Savings Goals
B2: Savings Goals
B4: Goal | C4: Target Amount | D4: Current Amount | E4: % Complete | F4: Target Date | G4: Monthly Contribution Needed
B5: Emergency Fund | C5: 15000 | D5: 9200 | E5: =D5/C5 -> 0.61333333 | F5: 46357 | G5: =IF(D5>=C5,0,(C5-D5)/MAX(1,DATEDIF(TODAY(),F5,"m"))) -> 1450
B6: Vacation | C6: 4000 | D6: 1600 | E6: =D6/C6 -> 0.4 | F6: 46266 | G6: =IF(D6>=C6,0,(C6-D6)/MAX(1,DATEDIF(TODAY(),F6,"m"))) -> 2400
B7: New Laptop | C7: 2200 | D7: 2200 | E7: =D7/C7 -> 1 | F7: 46082 | G7: =IF(D7>=C7,0,(C7-D7)/MAX(1,DATEDIF(TODAY(),F7,"m"))) -> 0
B8: House Down Payment | C8: 60000 | D8: 18500 | E8: =D8/C8 -> 0.30833333 | F8: 46905 | G8: =IF(D8>=C8,0,(C8-D8)/MAX(1,DATEDIF(TODAY(),F8,"m"))) -> 1886.3636

Sheet Investment Tracker
B2: Investment Tracker
B4: Holding | C4: Type | D4: Amount Invested | E4: Current Value | F4: Gain/Loss $ | G4: Gain/Loss % | H4: Allocation %
B5: S&P 500 Index | C5: ETF | D5: 12000 | E5: 13850 | F5: =E5-D5 -> 1850 | G5: =(E5-D5)/D5 -> 0.15416667 | H5: =E5/SUM($E$5:$E$9) -> 0.27093114
B6: Total Bond Market | C6: ETF | D6: 6000 | E6: 6120 | F6: =E6-D6 -> 120 | G6: =(E6-D6)/D6 -> 0.02 | H6: =E6/SUM($E$5:$E$9) -> 0.11971831
B7: Company 401k | C7: Retirement | D7: 22000 | E7: 25400 | F7: =E7-D7 -> 3400 | G7: =(E7-D7)/D7 -> 0.15454545 | H7: =E7/SUM($E$5:$E$9) -> 0.49687011
B8: Individual Stocks | C8: Equity | D8: 4000 | E8: 3650 | F8: =E8-D8 -> -350 | G8: =(E8-D8)/D8 -> -0.0875 | H8: =E8/SUM($E$5:$E$9) -> 0.071400626
B9: Crypto (BTC/ETH) | C9: Alt | D9: 1500 | E9: 2100 | F9: =E9-D9 -> 600 | G9: =(E9-D9)/D9 -> 0.4 | H9: =E9/SUM($E$5:$E$9) -> 0.041079812
B11: Total | D11: =SUM(D5:D9) -> 45500 | E11: =SUM(E5:E9) -> 51120 | F11: =E11-D11 -> 5620 | G11: =(E11-D11)/D11 -> 0.12351648

Sheet Subscription Tracker
B2: Subscription Tracker
B4: Service | C4: Monthly Cost | D4: Billing Cycle | E4: Category | F4: Annual Cost | G4: Status
B5: Netflix | C5: 15.49 | D5: Monthly | E5: Entertainment | F5: =C5*12 -> 185.88 | G5: Active
B6: Spotify | C6: 11.99 | D6: Monthly | E6: Entertainment | F6: =C6*12 -> 143.88 | G6: Active
B7: Gym Membership | C7: 55 | D7: Monthly | E7: Health & Fitness | F7: =C7*12 -> 660 | G7: Active
B8: Cloud Storage | C8: 9.99 | D8: Monthly | E8: Software | F8: =C8*12 -> 119.88 | G8: Active
B9: Meal Kit | C9: 64 | D9: Monthly | E9: Groceries | F9: =C9*12 -> 768 | G9: Cancelled
B10: News Subscription | C10: 8 | D10: Monthly | E10: Software | F10: =C10*12 -> 96 | G10: Active
B12: Total active annual cost | F12: =SUMIF(G5:G10,"Active",F5:F10) -> 1205.64

Sheet Net Worth Dashboard
B2: Net Worth Dashboard
B3: Update this snapshot monthly — Investments pulls live from the Investment Tracker total.
B5: Month | C5: Cash & Savings | D5: Investments | E5: Other Assets | F5: Total Liabilities | G5: Net Worth
B6: Jan 2026 | C6: 8600 | D6: 44800 | E6: 18000 | F6: 9200 | G6: =C6+D6+E6-F6 -> 62200
B7: Feb 2026 | C7: 9200 | D7: =SUM('Investment Tracker'!$E$5:$E$9) -> 51120 | E7: 18000 | F7: 8900 | G7: =C7+D7+E7-F7 -> 69420

Sheet Monthly Trends
B2: Monthly Trends
B4: Month | C4: Income | D4: Expenses | E4: Net Savings | F4: Savings Rate %
B5: Jan 2026 | C5: ='Income Tracker'!C8 -> 5764.2 | D5: ='Expense Tracker'!C8 -> 3269.73 | E5: =C5-D5 -> 2494.47 | F5: =E5/C5 -> 0.43275216
B6: Feb 2026 | C6: ='Income Tracker'!C9 -> 4815.8 | D6: ='Expense Tracker'!C9 -> 3072.18 | E6: =C6-D6 -> 1743.62 | F6: =E6/C6 -> 0.36206238

Sheet Spending Breakdown
B2: Spending Breakdown
B3: Month-over-month category comparison — where your spending is moving, not just where it landed.
B5: Category | C5: Jan 2026 | D5: Feb 2026 | E5: Change
B6: Dining | C6: =-SUMIFS(Transactions!$F$2:$F$65,Transactions!$D$2:$D$65,$B6,Transactions!$C$2:$C$65,"Expense",Transactions!$A$2:$A$65,">="&DATE(2026,1,1),Transactions!$A$2:$A$65,"<="&DATE(2026,1,31)) -> 7.25 | D6: =-SUMIFS(Transactions!$F$2:$F$65,Transactions!$D$2:$D$65,$B6,Transactions!$C$2:$C$65,"Expense",Transactions!$A$2:$A$65,">="&DATE(2026,2,1),Transactions!$A$2:$A$65,"<="&DATE(2026,2,28)) -> 0 | E6: =D6-C6 -> -7.25
B7: Groceries | C7: =-SUMIFS(Transactions!$F$2:$F$65,Transactions!$D$2:$D$65,$B7,Transactions!$C$2:$C$65,"Expense",Transactions!$A$2:$A$65,">="&DATE(2026,1,1),Transactions!$A$2:$A$65,"<="&DATE(2026,1,31)) -> 92.4 | D7: =-SUMIFS(Transactions!$F$2:$F$65,Transactions!$D$2:$D$65,$B7,Transactions!$C$2:$C$65,"Expense",Transactions!$A$2:$A$65,">="&DATE(2026,2,1),Transactions!$A$2:$A$65,"<="&DATE(2026,2,28)) -> 78.2 | E7: =D7-C7 -> -14.2
B8: Health & Fitness | C8: =-SUMIFS(Transactions!$F$2:$F$65,Transactions!$D$2:$D$65,$B8,Transactions!$C$2:$C$65,"Expense",Transactions!$A$2:$A$65,">="&DATE(2026,1,1),Transactions!$A$2:$A$65,"<="&DATE(2026,1,31)) -> 55 | D8: =-SUMIFS(Transactions!$F$2:$F$65,Transactions!$D$2:$D$65,$B8,Transactions!$C$2:$C$65,"Expense",Transactions!$A$2:$A$65,">="&DATE(2026,2,1),Transactions!$A$2:$A$65,"<="&DATE(2026,2,28)) -> 45 | E8: =D8-C8 -> -10
B9: Housing | C9: =-SUMIFS(Transactions!$F$2:$F$65,Transactions!$D$2:$D$65,$B9,Transactions!$C$2:$C$65,"Expense",Transactions!$A$2:$A$65,">="&DATE(2026,1,1),Transactions!$A$2:$A$65,"<="&DATE(2026,1,31)) -> 1800 | D9: =-SUMIFS(Transactions!$F$2:$F$65,Transactions!$D$2:$D$65,$B9,Transactions!$C$2:$C$65,"Expense",Transactions!$A$2:$A$65,">="&DATE(2026,2,1),Transactions!$A$2:$A$65,"<="&DATE(2026,2,28)) -> 1800 | E9: =D9-C9 -> 0
B10: Shopping | C10: =-SUMIFS(Transactions!$F$2:$F$65,Transactions!$D$2:$D$65,$B10,Transactions!$C$2:$C$65,"Expense",Transactions!$A$2:$A$65,">="&DATE(2026,1,1),Transactions!$A$2:$A$65,"<="&DATE(2026,1,31)) -> 68.1 | D10: =-SUMIFS(Transactions!$F$2:$F$65,Transactions!$D$2:$D$65,$B10,Transactions!$C$2:$C$65,"Expense",Transactions!$A$2:$A$65,">="&DATE(2026,2,1),Transactions!$A$2:$A$65,"<="&DATE(2026,2,28)) -> 0 | E10: =D10-C10 -> -68.1
B11: Subscriptions | C11: =-SUMIFS(Transactions!$F$2:$F$65,Transactions!$D$2:$D$65,$B11,Transactions!$C$2:$C$65,"Expense",Transactions!$A$2:$A$65,">="&DATE(2026,1,1),Transactions!$A$2:$A$65,"<="&DATE(2026,1,31)) -> 27.48 | D11: =-SUMIFS(Transactions!$F$2:$F$65,Transactions!$D$2:$D$65,$B11,Transactions!$C$2:$C$65,"Expense",Transactions!$A$2:$A$65,">="&DATE(2026,2,1),Transactions!$A$2:$A$65,"<="&DATE(2026,2,28)) -> 27.48 | E11: =D11-C11 -> 0
B12: Transport | C12: =-SUMIFS(Transactions!$F$2:$F$65,Transactions!$D$2:$D$65,$B12,Transactions!$C$2:$C$65,"Expense",Transactions!$A$2:$A$65,">="&DATE(2026,1,1),Transactions!$A$2:$A$65,"<="&DATE(2026,1,31)) -> 38.2 | D12: =-SUMIFS(Transactions!$F$2:$F$65,Transactions!$D$2:$D$65,$B12,Transactions!$C$2:$C$65,"Expense",Transactions!$A$2:$A$65,">="&DATE(2026,2,1),Transactions!$A$2:$A$65,"<="&DATE(2026,2,28)) -> 21.5 | E12: =D12-C12 -> -16.7
B13: Travel | C13: =-SUMIFS(Transactions!$F$2:$F$65,Transactions!$D$2:$D$65,$B13,Transactions!$C$2:$C$65,"Expense",Transactions!$A$2:$A$65,">="&DATE(2026,1,1),Transactions!$A$2:$A$65,"<="&DATE(2026,1,31)) -> 0 | D13: =-SUMIFS(Transactions!$F$2:$F$65,Transactions!$D$2:$D$65,$B13,Transactions!$C$2:$C$65,"Expense",Transactions!$A$2:$A$65,">="&DATE(2026,2,1),Transactions!$A$2:$A$65,"<="&DATE(2026,2,28)) -> 0 | E13: =D13-C13 -> 0
B14: Utilities | C14: =-SUMIFS(Transactions!$F$2:$F$65,Transactions!$D$2:$D$65,$B14,Transactions!$C$2:$C$65,"Expense",Transactions!$A$2:$A$65,">="&DATE(2026,1,1),Transactions!$A$2:$A$65,"<="&DATE(2026,1,31)) -> 81.3 | D14: =-SUMIFS(Transactions!$F$2:$F$65,Transactions!$D$2:$D$65,$B14,Transactions!$C$2:$C$65,"Expense",Transactions!$A$2:$A$65,">="&DATE(2026,2,1),Transactions!$A$2:$A$65,"<="&DATE(2026,2,28)) -> 0 | E14: =D14-C14 -> -81.3

Sheet Financial Health Score
B2: Financial Health Score
B3: Three real inputs, no hidden weighting — see exactly how the score is built.
B5: Component | C5: Score (0-100) | D5: How it's calculated
B6: Savings Rate | C6: =MIN(100,('Monthly Trends'!F6/0.25)*100) -> 100 | D6: Your latest month's savings rate, scaled so a 25% savings rate = 100 points.
B7: Emergency Fund Coverage | C7: =MIN(100,('Net Worth Dashboard'!C7/(3*'Expense Tracker'!C9))*100) -> 99.82054 | D7: Cash & savings divided by 3 months of your latest expenses, scaled so full 3-month coverage = 100 points.
B8: Subscription Load | C8: =MAX(0,100-(('Subscription Tracker'!F12/12)/'Income Tracker'!C9)*500) -> 89.568711 | D8: Active monthly subscription cost as a share of income, scaled so subscriptions at 20%+ of income = 0 points.
B10: Overall Health Score | C10: =AVERAGE(C6:C8) -> 96.463084
C11: =IF(C10>=85,"Excellent",IF(C10>=70,"Good",IF(C10>=40,"Fair","Needs Attention"))) -> Excellent

Sheet Annual Summary Dashboard
B2: Annual Summary Dashboard
B3: Every tab in this workbook, in one page.
B5: Total Income (YTD) | C5: Total Expenses (YTD) | D5: Net Savings (YTD) | E5: Net Worth (latest) | F5: Health Score
B6: =SUM('Income Tracker'!C8:C9) -> 10580 | C6: =SUM('Expense Tracker'!C8:C9) -> 6341.91 | D6: =B6-C6 -> 4238.09 | E6: ='Net Worth Dashboard'!G7 -> 69420 | F6: ='Financial Health Score'!C10 -> 96.463084
B25: Top spending categories (Feb 2026)
B27: Category | C27: Amount
B28: =INDEX('Spending Breakdown'!$B$6:$B$14,MATCH(LARGE('Spending Breakdown'!$D$6:$D$14,1),'Spending Breakdown'!$D$6:$D$14,0)) -> Housing | C28: =LARGE('Spending Breakdown'!$D$6:$D$14,1) -> 1800
B29: =INDEX('Spending Breakdown'!$B$6:$B$14,MATCH(LARGE('Spending Breakdown'!$D$6:$D$14,2),'Spending Breakdown'!$D$6:$D$14,0)) -> Groceries | C29: =LARGE('Spending Breakdown'!$D$6:$D$14,2) -> 78.2
B30: =INDEX('Spending Breakdown'!$B$6:$B$14,MATCH(LARGE('Spending Breakdown'!$D$6:$D$14,3),'Spending Breakdown'!$D$6:$D$14,0)) -> Health & Fitness | C30: =LARGE('Spending Breakdown'!$D$6:$D$14,3) -> 45
B31: =INDEX('Spending Breakdown'!$B$6:$B$14,MATCH(LARGE('Spending Breakdown'!$D$6:$D$14,4),'Spending Breakdown'!$D$6:$D$14,0)) -> Subscriptions | C31: =LARGE('Spending Breakdown'!$D$6:$D$14,4) -> 27.48
B32: =INDEX('Spending Breakdown'!$B$6:$B$14,MATCH(LARGE('Spending Breakdown'!$D$6:$D$14,5),'Spending Breakdown'!$D$6:$D$14,0)) -> Transport | C32: =LARGE('Spending Breakdown'!$D$6:$D$14,5) -> 21.5
