Workbook

Sheet Read Me
B2: Personal Budget Tracker
B3: Monthly income vs. expense tracker with keyword auto-categorization and a savings-rate dashboard.
B5: How to use this workbook
B7: 1. Transactions
B8: Log every transaction on the Transactions tab: date, description, amount, and whether it's income or an expense. Type a description and the Suggested Category column will auto-guess a category by matching keywords (e.g. "starbucks" -> Dining). Use the Category dropdown to confirm or override it.
B10: 2. Keywords
B11: This is the lookup table powering auto-categorization. Add your own recurring merchants and their category so future transactions categorize themselves automatically.
B13: 3. Monthly Summary
B14: Every month rolls up automatically from your Transactions using SUMIFS formulas — nothing to copy or recalculate by hand. Add a new month by adding a row and copying the formulas down.
B16: 4. Dashboard
B17: Scorecards, a savings-rate trend, and a spending-by-category breakdown — all driven live from your data. Everything recalculates the moment you add a new transaction.
B19: Notes
... B25: Built by Simran Tiwari — simrant.github.io

Sheet Keywords
A1: Keyword (lowercase, partial match) | B1: Category
A2: starbucks | B2: Dining
A3: coffee | B3: Dining
A4: restaurant | B4: Dining
A5: doordash | B5: Dining
A6: ubereats | B6: Dining
A7: mcdonald | B7: Dining
A8: grocery | B8: Groceries
A9: trader joe | B9: Groceries
A10: whole foods | B10: Groceries
A11: safeway | B11: Groceries
A12: uber | B12: Transport
... A41: transfer to savings | B41: Savings

Sheet Transactions
A1: Date | B1: Description | C1: Type | D1: Category | E1: Suggested Category | F1: Amount
A2: 46025 | B2: Payroll deposit | C2: Income | D2: Income | E2: =IFERROR(INDEX(Keywords!$B$2:$B$41,SUMPRODUCT(MAX((ISNUMBER(SEARCH(Keywords!$A$2:$A$41,B2)))*ROW(Keywords!$A$2:$A$41)))-1),"Uncategorized") -> Income | F2: 4200
A3: 46026 | B3: Whole Foods grocery run | C3: Expense | D3: Groceries | E3: =IFERROR(INDEX(Keywords!$B$2:$B$41,SUMPRODUCT(MAX((ISNUMBER(SEARCH(Keywords!$A$2:$A$41,B3)))*ROW(Keywords!$A$2:$A$41)))-1),"Uncategorized") -> Groceries | F3: -86.4
A4: 46027 | B4: Starbucks coffee | C4: Expense | D4: Dining | E4: =IFERROR(INDEX(Keywords!$B$2:$B$41,SUMPRODUCT(MAX((ISNUMBER(SEARCH(Keywords!$A$2:$A$41,B4)))*ROW(Keywords!$A$2:$A$41)))-1),"Uncategorized") -> Dining | F4: -6.75
A5: 46028 | B5: Rent payment | C5: Expense | D5: Housing | E5: =IFERROR(INDEX(Keywords!$B$2:$B$41,SUMPRODUCT(MAX((ISNUMBER(SEARCH(Keywords!$A$2:$A$41,B5)))*ROW(Keywords!$A$2:$A$41)))-1),"Uncategorized") -> Housing | F5: -1650
A6: 46030 | B6: Uber to airport | C6: Expense | D6: Transport | E6: =IFERROR(INDEX(Keywords!$B$2:$B$41,SUMPRODUCT(MAX((ISNUMBER(SEARCH(Keywords!$A$2:$A$41,B6)))*ROW(Keywords!$A$2:$A$41)))-1),"Uncategorized") -> Transport | F6: -34.2
A7: 46032 | B7: Netflix subscription | C7: Expense | D7: Subscriptions | E7: =IFERROR(INDEX(Keywords!$B$2:$B$41,SUMPRODUCT(MAX((ISNUMBER(SEARCH(Keywords!$A$2:$A$41,B7)))*ROW(Keywords!$A$2:$A$41)))-1),"Uncategorized") -> Subscriptions | F7: -15.49
A8: 46034 | B8: Gym membership | C8: Expense | D8: Health & Fitness | E8: =IFERROR(INDEX(Keywords!$B$2:$B$41,SUMPRODUCT(MAX((ISNUMBER(SEARCH(Keywords!$A$2:$A$41,B8)))*ROW(Keywords!$A$2:$A$41)))-1),"Uncategorized") -> Health & Fitness | F8: -49
A9: 46037 | B9: Freelance project payment | C9: Income | D9: Income | E9: =IFERROR(INDEX(Keywords!$B$2:$B$41,SUMPRODUCT(MAX((ISNUMBER(SEARCH(Keywords!$A$2:$A$41,B9)))*ROW(Keywords!$A$2:$A$41)))-1),"Uncategorized") -> Income | F9: 800
A10: 46040 | B10: Amazon order | C10: Expense | D10: Shopping | E10: =IFERROR(INDEX(Keywords!$B$2:$B$41,SUMPRODUCT(MAX((ISNUMBER(SEARCH(Keywords!$A$2:$A$41,B10)))*ROW(Keywords!$A$2:$A$41)))-1),"Uncategorized") -> Shopping | F10: -62.1
A11: 46042 | B11: Electric bill | C11: Expense | D11: Utilities | E11: =IFERROR(INDEX(Keywords!$B$2:$B$41,SUMPRODUCT(MAX((ISNUMBER(SEARCH(Keywords!$A$2:$A$41,B11)))*ROW(Keywords!$A$2:$A$41)))-1),"Uncategorized") -> Utilities | F11: -74.3
A12: 46044 | B12: Transfer to savings | C12: Expense | D12: Savings | E12: =IFERROR(INDEX(Keywords!$B$2:$B$41,SUMPRODUCT(MAX((ISNUMBER(SEARCH(Keywords!$A$2:$A$41,B12)))*ROW(Keywords!$A$2:$A$41)))-1),"Uncategorized") -> Savings | F12: -400
A13: 46047 | B13: Trader Joe's grocery run | C13: Expense | D13: Groceries | E13: =IFERROR(INDEX(Keywords!$B$2:$B$41,SUMPRODUCT(MAX((ISNUMBER(SEARCH(Keywords!$A$2:$A$41,B13)))*ROW(Keywords!$A$2:$A$41)))-1),"Uncategorized") -> Groceries | F13: -58.9
... A21: 46079 | B21: Interest earned | C21: Income | D21: Income | E21: =IFERROR(INDEX(Keywords!$B$2:$B$41,SUMPRODUCT(MAX((ISNUMBER(SEARCH(Keywords!$A$2:$A$41,B21)))*ROW(Keywords!$A$2:$A$41)))-1),"Uncategorized") -> Income | F21: 12.3
E22: =IF(B22="","",IFERROR(INDEX(Keywords!$B$2:$B$41,SUMPRODUCT(MAX((ISNUMBER(SEARCH(Keywords!$A$2:$A$41,B22)))*ROW(Keywords!$A$2:$A$41)))-1),"Uncategorized"))
E23: =IF(B23="","",IFERROR(INDEX(Keywords!$B$2:$B$41,SUMPRODUCT(MAX((ISNUMBER(SEARCH(Keywords!$A$2:$A$41,B23)))*ROW(Keywords!$A$2:$A$41)))-1),"Uncategorized"))
E24: =IF(B24="","",IFERROR(INDEX(Keywords!$B$2:$B$41,SUMPRODUCT(MAX((ISNUMBER(SEARCH(Keywords!$A$2:$A$41,B24)))*ROW(Keywords!$A$2:$A$41)))-1),"Uncategorized"))
E25: =IF(B25="","",IFERROR(INDEX(Keywords!$B$2:$B$41,SUMPRODUCT(MAX((ISNUMBER(SEARCH(Keywords!$A$2:$A$41,B25)))*ROW(Keywords!$A$2:$A$41)))-1),"Uncategorized"))
E26: =IF(B26="","",IFERROR(INDEX(Keywords!$B$2:$B$41,SUMPRODUCT(MAX((ISNUMBER(SEARCH(Keywords!$A$2:$A$41,B26)))*ROW(Keywords!$A$2:$A$41)))-1),"Uncategorized"))
E27: =IF(B27="","",IFERROR(INDEX(Keywords!$B$2:$B$41,SUMPRODUCT(MAX((ISNUMBER(SEARCH(Keywords!$A$2:$A$41,B27)))*ROW(Keywords!$A$2:$A$41)))-1),"Uncategorized"))
E28: =IF(B28="","",IFERROR(INDEX(Keywords!$B$2:$B$41,SUMPRODUCT(MAX((ISNUMBER(SEARCH(Keywords!$A$2:$A$41,B28)))*ROW(Keywords!$A$2:$A$41)))-1),"Uncategorized"))
E29: =IF(B29="","",IFERROR(INDEX(Keywords!$B$2:$B$41,SUMPRODUCT(MAX((ISNUMBER(SEARCH(Keywords!$A$2:$A$41,B29)))*ROW(Keywords!$A$2:$A$41)))-1),"Uncategorized"))
E30: =IF(B30="","",IFERROR(INDEX(Keywords!$B$2:$B$41,SUMPRODUCT(MAX((ISNUMBER(SEARCH(Keywords!$A$2:$A$41,B30)))*ROW(Keywords!$A$2:$A$41)))-1),"Uncategorized"))
E31: =IF(B31="","",IFERROR(INDEX(Keywords!$B$2:$B$41,SUMPRODUCT(MAX((ISNUMBER(SEARCH(Keywords!$A$2:$A$41,B31)))*ROW(Keywords!$A$2:$A$41)))-1),"Uncategorized"))
E32: =IF(B32="","",IFERROR(INDEX(Keywords!$B$2:$B$41,SUMPRODUCT(MAX((ISNUMBER(SEARCH(Keywords!$A$2:$A$41,B32)))*ROW(Keywords!$A$2:$A$41)))-1),"Uncategorized"))
E33: =IF(B33="","",IFERROR(INDEX(Keywords!$B$2:$B$41,SUMPRODUCT(MAX((ISNUMBER(SEARCH(Keywords!$A$2:$A$41,B33)))*ROW(Keywords!$A$2:$A$41)))-1),"Uncategorized"))
... E51: =IF(B51="","",IFERROR(INDEX(Keywords!$B$2:$B$41,SUMPRODUCT(MAX((ISNUMBER(SEARCH(Keywords!$A$2:$A$41,B51)))*ROW(Keywords!$A$2:$A$41)))-1),"Uncategorized"))

Sheet Category Breakdown
A1: Category | B1: Jan 2026 | C1: Feb 2026
A2: Dining | B2: =-SUMIFS(Transactions!$F$2:$F$51,Transactions!$D$2:$D$51,$A2,Transactions!$C$2:$C$51,"Expense",Transactions!$A$2:$A$51,">="&DATE(2026,1,1),Transactions!$A$2:$A$51,"<="&DATE(2026,1,31)) -> 6.75 | C2: =-SUMIFS(Transactions!$F$2:$F$51,Transactions!$D$2:$D$51,$A2,Transactions!$C$2:$C$51,"Expense",Transactions!$A$2:$A$51,">="&DATE(2026,2,1),Transactions!$A$2:$A$51,"<="&DATE(2026,2,28)) -> 0
A3: Groceries | B3: =-SUMIFS(Transactions!$F$2:$F$51,Transactions!$D$2:$D$51,$A3,Transactions!$C$2:$C$51,"Expense",Transactions!$A$2:$A$51,">="&DATE(2026,1,1),Transactions!$A$2:$A$51,"<="&DATE(2026,1,31)) -> 145.3 | C3: =-SUMIFS(Transactions!$F$2:$F$51,Transactions!$D$2:$D$51,$A3,Transactions!$C$2:$C$51,"Expense",Transactions!$A$2:$A$51,">="&DATE(2026,2,1),Transactions!$A$2:$A$51,"<="&DATE(2026,2,28)) -> 71.2
A4: Health & Fitness | B4: =-SUMIFS(Transactions!$F$2:$F$51,Transactions!$D$2:$D$51,$A4,Transactions!$C$2:$C$51,"Expense",Transactions!$A$2:$A$51,">="&DATE(2026,1,1),Transactions!$A$2:$A$51,"<="&DATE(2026,1,31)) -> 49 | C4: =-SUMIFS(Transactions!$F$2:$F$51,Transactions!$D$2:$D$51,$A4,Transactions!$C$2:$C$51,"Expense",Transactions!$A$2:$A$51,">="&DATE(2026,2,1),Transactions!$A$2:$A$51,"<="&DATE(2026,2,28)) -> 40
A5: Housing | B5: =-SUMIFS(Transactions!$F$2:$F$51,Transactions!$D$2:$D$51,$A5,Transactions!$C$2:$C$51,"Expense",Transactions!$A$2:$A$51,">="&DATE(2026,1,1),Transactions!$A$2:$A$51,"<="&DATE(2026,1,31)) -> 1650 | C5: =-SUMIFS(Transactions!$F$2:$F$51,Transactions!$D$2:$D$51,$A5,Transactions!$C$2:$C$51,"Expense",Transactions!$A$2:$A$51,">="&DATE(2026,2,1),Transactions!$A$2:$A$51,"<="&DATE(2026,2,28)) -> 1650
A6: Savings | B6: =-SUMIFS(Transactions!$F$2:$F$51,Transactions!$D$2:$D$51,$A6,Transactions!$C$2:$C$51,"Expense",Transactions!$A$2:$A$51,">="&DATE(2026,1,1),Transactions!$A$2:$A$51,"<="&DATE(2026,1,31)) -> 400 | C6: =-SUMIFS(Transactions!$F$2:$F$51,Transactions!$D$2:$D$51,$A6,Transactions!$C$2:$C$51,"Expense",Transactions!$A$2:$A$51,">="&DATE(2026,2,1),Transactions!$A$2:$A$51,"<="&DATE(2026,2,28)) -> 400
A7: Shopping | B7: =-SUMIFS(Transactions!$F$2:$F$51,Transactions!$D$2:$D$51,$A7,Transactions!$C$2:$C$51,"Expense",Transactions!$A$2:$A$51,">="&DATE(2026,1,1),Transactions!$A$2:$A$51,"<="&DATE(2026,1,31)) -> 62.1 | C7: =-SUMIFS(Transactions!$F$2:$F$51,Transactions!$D$2:$D$51,$A7,Transactions!$C$2:$C$51,"Expense",Transactions!$A$2:$A$51,">="&DATE(2026,2,1),Transactions!$A$2:$A$51,"<="&DATE(2026,2,28)) -> 0
A8: Subscriptions | B8: =-SUMIFS(Transactions!$F$2:$F$51,Transactions!$D$2:$D$51,$A8,Transactions!$C$2:$C$51,"Expense",Transactions!$A$2:$A$51,">="&DATE(2026,1,1),Transactions!$A$2:$A$51,"<="&DATE(2026,1,31)) -> 15.49 | C8: =-SUMIFS(Transactions!$F$2:$F$51,Transactions!$D$2:$D$51,$A8,Transactions!$C$2:$C$51,"Expense",Transactions!$A$2:$A$51,">="&DATE(2026,2,1),Transactions!$A$2:$A$51,"<="&DATE(2026,2,28)) -> 11.99
A9: Transport | B9: =-SUMIFS(Transactions!$F$2:$F$51,Transactions!$D$2:$D$51,$A9,Transactions!$C$2:$C$51,"Expense",Transactions!$A$2:$A$51,">="&DATE(2026,1,1),Transactions!$A$2:$A$51,"<="&DATE(2026,1,31)) -> 34.2 | C9: =-SUMIFS(Transactions!$F$2:$F$51,Transactions!$D$2:$D$51,$A9,Transactions!$C$2:$C$51,"Expense",Transactions!$A$2:$A$51,">="&DATE(2026,2,1),Transactions!$A$2:$A$51,"<="&DATE(2026,2,28)) -> 18.5
A10: Travel | B10: =-SUMIFS(Transactions!$F$2:$F$51,Transactions!$D$2:$D$51,$A10,Transactions!$C$2:$C$51,"Expense",Transactions!$A$2:$A$51,">="&DATE(2026,1,1),Transactions!$A$2:$A$51,"<="&DATE(2026,1,31)) -> 0 | C10: =-SUMIFS(Transactions!$F$2:$F$51,Transactions!$D$2:$D$51,$A10,Transactions!$C$2:$C$51,"Expense",Transactions!$A$2:$A$51,">="&DATE(2026,2,1),Transactions!$A$2:$A$51,"<="&DATE(2026,2,28)) -> 0
A11: Utilities | B11: =-SUMIFS(Transactions!$F$2:$F$51,Transactions!$D$2:$D$51,$A11,Transactions!$C$2:$C$51,"Expense",Transactions!$A$2:$A$51,">="&DATE(2026,1,1),Transactions!$A$2:$A$51,"<="&DATE(2026,1,31)) -> 74.3 | C11: =-SUMIFS(Transactions!$F$2:$F$51,Transactions!$D$2:$D$51,$A11,Transactions!$C$2:$C$51,"Expense",Transactions!$A$2:$A$51,">="&DATE(2026,2,1),Transactions!$A$2:$A$51,"<="&DATE(2026,2,28)) -> 0

Sheet Monthly Summary
A1: Month | B1: Total Income | C1: Total Expenses | D1: Net Savings | E1: Savings Rate % | F1: Top Category | H1: Start | I1: End
B2: =SUMIFS(Transactions!$F$2:$F$51,Transactions!$A$2:$A$51,">="&H2,Transactions!$A$2:$A$51,"<="&I2,Transactions!$C$2:$C$51,"Income") -> 5000 | C2: =-SUMIFS(Transactions!$F$2:$F$51,Transactions!$A$2:$A$51,">="&H2,Transactions!$A$2:$A$51,"<="&I2,Transactions!$C$2:$C$51,"Expense") -> 2437.14 | D2: =B2-C2 -> 2562.86 | E2: =IF(B2=0,"",D2/B2) -> 0.512572 | F2: =IFERROR(INDEX('Category Breakdown'!$A$2:$A$11,MATCH(MAX('Category Breakdown'!$B$2:$B$11),'Category Breakdown'!$B$2:$B$11,0)),"-") -> Housing | H2: 46023 | I2: 46053
B3: =SUMIFS(Transactions!$F$2:$F$51,Transactions!$A$2:$A$51,">="&H3,Transactions!$A$2:$A$51,"<="&I3,Transactions!$C$2:$C$51,"Income") -> 4212.3 | C3: =-SUMIFS(Transactions!$F$2:$F$51,Transactions!$A$2:$A$51,">="&H3,Transactions!$A$2:$A$51,"<="&I3,Transactions!$C$2:$C$51,"Expense") -> 2191.69 | D3: =B3-C3 -> 2020.61 | E3: =IF(B3=0,"",D3/B3) -> 0.4796928 | F3: =IFERROR(INDEX('Category Breakdown'!$A$2:$A$11,MATCH(MAX('Category Breakdown'!$C$2:$C$11),'Category Breakdown'!$C$2:$C$11,0)),"-") -> Housing | H3: 46054 | I3: 46081

Sheet Dashboard
B2: Personal Budget Dashboard
B3: Live snapshot — every number below recalculates from the Transactions tab
B5: Total Income (YTD) | C5: Total Expenses (YTD) | D5: Net Savings (YTD) | E5: Avg Savings Rate
B6: =SUM('Monthly Summary'!B2:B3) -> 9212.3 | C6: =SUM('Monthly Summary'!C2:C3) -> 4628.83 | D6: =SUM('Monthly Summary'!D2:D3) -> 4583.47 | E6: =AVERAGE('Monthly Summary'!E2:E3) -> 0.4961324
B26: Spending by category (YTD)
B27: Category | C27: Total Spent
B28: Dining | C28: =-SUMIFS(Transactions!$F$2:$F$51,Transactions!$D$2:$D$51,B28,Transactions!$C$2:$C$51,"Expense") -> 6.75
B29: Groceries | C29: =-SUMIFS(Transactions!$F$2:$F$51,Transactions!$D$2:$D$51,B29,Transactions!$C$2:$C$51,"Expense") -> 216.5
B30: Health & Fitness | C30: =-SUMIFS(Transactions!$F$2:$F$51,Transactions!$D$2:$D$51,B30,Transactions!$C$2:$C$51,"Expense") -> 89
B31: Housing | C31: =-SUMIFS(Transactions!$F$2:$F$51,Transactions!$D$2:$D$51,B31,Transactions!$C$2:$C$51,"Expense") -> 3300
B32: Savings | C32: =-SUMIFS(Transactions!$F$2:$F$51,Transactions!$D$2:$D$51,B32,Transactions!$C$2:$C$51,"Expense") -> 800
B33: Shopping | C33: =-SUMIFS(Transactions!$F$2:$F$51,Transactions!$D$2:$D$51,B33,Transactions!$C$2:$C$51,"Expense") -> 62.1
B34: Subscriptions | C34: =-SUMIFS(Transactions!$F$2:$F$51,Transactions!$D$2:$D$51,B34,Transactions!$C$2:$C$51,"Expense") -> 27.48
B35: Transport | C35: =-SUMIFS(Transactions!$F$2:$F$51,Transactions!$D$2:$D$51,B35,Transactions!$C$2:$C$51,"Expense") -> 52.7
B36: Travel | C36: =-SUMIFS(Transactions!$F$2:$F$51,Transactions!$D$2:$D$51,B36,Transactions!$C$2:$C$51,"Expense") -> 0
B37: Utilities | C37: =-SUMIFS(Transactions!$F$2:$F$51,Transactions!$D$2:$D$51,B37,Transactions!$C$2:$C$51,"Expense") -> 74.3
